{"cameraMode":{"drawMode":0,"name":"Shaded","section":"Shading Mode"},"sceneLighting":false,"audioPlay":false,"sceneViewState":{"m_AlwaysRefresh":false,"showFog":true,"showSkybox":false,"showFlares":true,"showImageEffects":true,"showParticleSystems":true,"showVisualEffectGraphs":true,"m_FxEnabled":true},"in2DMode":false,"pivot":{"x":-4.619606018066406,"y":0.0716254711151123,"z":2.050906181335449},"rotation":{"x":-0.05373969301581383,"y":-0.6076834201812744,"z":0.041270025074481967,"w":-0.7912863492965698},"size":1.3040052652359009,"orthographic":false}